nti.recipes.zodb-1.1.0-py3.8-nspkg.pth
nti/recipes/zodb/__init__.py
nti/recipes/zodb/_model.py
nti/recipes/zodb/relstorage.py
nti/recipes/zodb/zeo.py
nti/recipes/zodb/tests/__init__.py
nti/recipes/zodb/tests/test__model.py
nti/recipes/zodb/tests/test_readme.py
nti/recipes/zodb/tests/test_relstorage.py
nti/recipes/zodb/tests/test_zeo.py
nti.recipes.zodb-1.1.0.dist-info/LICENSE
nti.recipes.zodb-1.1.0.dist-info/METADATA
nti.recipes.zodb-1.1.0.dist-info/WHEEL
nti.recipes.zodb-1.1.0.dist-info/entry_points.txt
nti.recipes.zodb-1.1.0.dist-info/namespace_packages.txt
nti.recipes.zodb-1.1.0.dist-info/top_level.txt
nti.recipes.zodb-1.1.0.dist-info/RECORD
